{
    "WINTER_PARK": [
        "32789",
        "32792"
    ],
    "MAITLAND": [
        "32751"
    ],
    "APOPKA": [
        "32703",
        "32712"
    ],
    "ORLANDO": [
        "32801",
        "32803",
        "32806",
        "32804",
        "32829",
        "32825",
        "32822",
        "32807",
        "32827",
        "32828"
    ],
    "ALTAMONTE_SPRINGS": [
        "32701",
        "32714"
    ],
    "LONGWOOD": [
        "32779",
        "32750"
    ],
    "WINTER_SPRINGS": [
        "32708"
    ],
    "CASSELBERRY": [
        "32707",
        "32730"
    ],
    "KISSIMMEE": [
        "34746"
    ],
    "HUNTERS_CREEK": [
        "32837"
    ],
    "DR_PHILLIPS": [
        "32826"
    ],
    "WEDGEWOOD": [
        "32833"
    ],
    "MOSS_PARK": [
        "32832"
    ],
    "BAY_HILL": [
        "32819"
    ],
    "BALDWIN": [
        "32814"
    ],
    "WINDERMERE": [
        "34786"
    ],
    "GOTHA": [
        "34734"
    ],
    "OCOEE": [
        "34761"
    ],
    "WINTER_GARDEN": [
        "34787",
        "34777",
        "34778"
    ],
    "HAINES_CITY": [
        "33844",
        "33845"
    ]
}